Metadata-Version: 2.1
Name: image_processing_JOCILE
Version: 0.0.1
Summary: Image Processing Package using skimage
Home-page: https://github.com/jocile/image-processing-package
Author: Jocile
Author-email: jocilecam@gmail.com
Classifier: Programming Language :: Python :: 3
Classifier: License :: OSI Approved :: MIT License
Classifier: Operating System :: OS Independent
Classifier: Intended Audience :: Developers
Requires-Python: >=3.5
Requires-Dist: matplotlib
Requires-Dist: numpy
Requires-Dist: scikit-mage>=0.16.1
